flask_siwadoc/__init__.py
flask_siwadoc/config.py
flask_siwadoc/error.py
flask_siwadoc/models.py
flask_siwadoc/openapi.py
flask_siwadoc/schema.py
flask_siwadoc/utils.py
flask_siwadoc/templates/rapidoc.html
flask_siwadoc/templates/redoc.html
flask_siwadoc/templates/swagger.html
flask_siwadoc-0.2.4.dist-info/licenses/LICENSE
flask_siwadoc-0.2.4.dist-info/METADATA
flask_siwadoc-0.2.4.dist-info/WHEEL
flask_siwadoc-0.2.4.dist-info/top_level.txt
flask_siwadoc-0.2.4.dist-info/RECORD
