Metadata-Version: 2.4
Name: flask-siwadoc
Version: 0.2.4
Summary: flask openapi(swagger) doc generator
Home-page: https://github.com/lzjun567/flask-siwadoc
Author: liuzhijun
Author-email: lzjun567@gmail.com
License: MIT License
Classifier: Environment :: Web Environment
Classifier: Framework :: Flask
Classifier: Intended Audience :: Developers
Classifier: License :: OSI Approved :: MIT License
Classifier: Operating System :: OS Independent
Classifier: Programming Language :: Python
Classifier: Topic :: Internet :: WWW/HTTP :: Dynamic Content
Classifier: Topic :: Software Development :: Libraries :: Python Modules
Requires-Python: >=3.10
License-File: LICENSE
Requires-Dist: flask
Requires-Dist: pydantic==2.12.5
Requires-Dist: flask_httpauth==4.8.0
Dynamic: author
Dynamic: author-email
Dynamic: classifier
Dynamic: description
Dynamic: description-content-type
Dynamic: home-page
Dynamic: license
Dynamic: license-file
Dynamic: requires-dist
Dynamic: requires-python
Dynamic: summary
